airbyte_cdk/__init__.py
airbyte_cdk/config_observation.py
airbyte_cdk/connector.py
airbyte_cdk/entrypoint.py
airbyte_cdk/exception_handler.py
airbyte_cdk/logger.py
airbyte_cdk/py.typed
airbyte_cdk/destinations/__init__.py
airbyte_cdk/destinations/destination.py
airbyte_cdk/models/__init__.py
airbyte_cdk/models/airbyte_protocol.py
airbyte_cdk/models/well_known_types.py
airbyte_cdk/sources/__init__.py
airbyte_cdk/sources/abstract_source.py
airbyte_cdk/sources/config.py
airbyte_cdk/sources/connector_state_manager.py
airbyte_cdk/sources/source.py
airbyte_cdk/sources/declarative/__init__.py
airbyte_cdk/sources/declarative/create_partial.py
airbyte_cdk/sources/declarative/declarative_component_schema.yaml
airbyte_cdk/sources/declarative/declarative_source.py
airbyte_cdk/sources/declarative/declarative_stream.py
airbyte_cdk/sources/declarative/exceptions.py
airbyte_cdk/sources/declarative/manifest_declarative_source.py
airbyte_cdk/sources/declarative/types.py
airbyte_cdk/sources/declarative/yaml_declarative_source.py
airbyte_cdk/sources/declarative/auth/__init__.py
airbyte_cdk/sources/declarative/auth/declarative_authenticator.py
airbyte_cdk/sources/declarative/auth/oauth.py
airbyte_cdk/sources/declarative/auth/token.py
airbyte_cdk/sources/declarative/checks/__init__.py
airbyte_cdk/sources/declarative/checks/check_stream.py
airbyte_cdk/sources/declarative/checks/connection_checker.py
airbyte_cdk/sources/declarative/datetime/__init__.py
airbyte_cdk/sources/declarative/datetime/datetime_parser.py
airbyte_cdk/sources/declarative/datetime/min_max_datetime.py
airbyte_cdk/sources/declarative/decoders/__init__.py
airbyte_cdk/sources/declarative/decoders/decoder.py
airbyte_cdk/sources/declarative/decoders/json_decoder.py
airbyte_cdk/sources/declarative/extractors/__init__.py
airbyte_cdk/sources/declarative/extractors/dpath_extractor.py
airbyte_cdk/sources/declarative/extractors/http_selector.py
airbyte_cdk/sources/declarative/extractors/record_extractor.py
valmi_airbyte_cdk-0.30.3.dist-info/LICENSE.txt
valmi_airbyte_cdk-0.30.3.dist-info/METADATA
valmi_airbyte_cdk-0.30.3.dist-info/WHEEL
valmi_airbyte_cdk-0.30.3.dist-info/top_level.txt
valmi_airbyte_cdk-0.30.3.dist-info/RECORD
