Metadata-Version: 2.1
Name: valmi-airbyte-cdk
Version: 0.30.3
Summary: A framework for writing Airbyte Connectors.
Home-page: https://github.com/airbytehq/airbyte
Author: Airbyte
Author-email: contact@airbyte.io
License: MIT
Project-URL: Documentation, https://docs.airbyte.io/
Project-URL: Source, https://github.com/airbytehq/airbyte
Project-URL: Tracker, https://github.com/airbytehq/airbyte/issues
Keywords: airbyte connector-development-kit cdk
Classifier: Development Status :: 3 - Alpha
Classifier: Intended Audience :: Developers
Classifier: Topic :: Scientific/Engineering
Classifier: Topic :: Software Development :: Libraries :: Python Modules
Classifier: License :: OSI Approved :: MIT License
Classifier: Programming Language :: Python :: 3.8
Requires-Python: >=3.8
License-File: LICENSE.txt
Requires-Dist: airbyte-protocol-models (==1.0.0)
Requires-Dist: backoff
Requires-Dist: dpath (~=2.0.1)
Requires-Dist: isodate (~=0.6.1)
Requires-Dist: jsonschema (~=3.2.0)
Requires-Dist: jsonref (~=0.2)
Requires-Dist: pendulum
Requires-Dist: genson (==1.2.2)
Requires-Dist: pydantic (~=1.9.2)
Requires-Dist: python-dateutil
Requires-Dist: PyYAML (>=6)
Requires-Dist: requests
Requires-Dist: requests-cache
Requires-Dist: Deprecated (~=1.2)
Requires-Dist: Jinja2 (~=3.1.2)
Requires-Dist: cachetools
Provides-Extra: dev
Requires-Dist: freezegun ; extra == 'dev'
Requires-Dist: MyPy (~=0.812) ; extra == 'dev'
Requires-Dist: pytest ; extra == 'dev'
Requires-Dist: pytest-cov ; extra == 'dev'
Requires-Dist: pytest-mock ; extra == 'dev'
Requires-Dist: requests-mock ; extra == 'dev'
Requires-Dist: pytest-httpserver ; extra == 'dev'
Provides-Extra: sphinx-docs
Requires-Dist: Sphinx (~=4.2) ; extra == 'sphinx-docs'
Requires-Dist: sphinx-rtd-theme (~=1.0) ; extra == 'sphinx-docs'
